rltorch/__init__.py
rltorch/agent/__init__.py
rltorch/agent/base.py
rltorch/agent/utils.py
rltorch/agent/apex/__init__.py
rltorch/agent/apex/actor.py
rltorch/agent/apex/base.py
rltorch/agent/apex/learner.py
rltorch/agent/sac/__init__.py
rltorch/agent/sac/actor.py
rltorch/agent/sac/base.py
rltorch/agent/sac/learner.py
rltorch/agent/sac_discrete/__init__.py
rltorch/agent/sac_discrete/actor.py
rltorch/agent/sac_discrete/base.py
rltorch/agent/sac_discrete/learner.py
rltorch/distributed/__init__.py
rltorch/distributed/run.py
rltorch/env/__init__.py
rltorch/env/atari_wrappers.py
rltorch/memory/__init__.py
rltorch/memory/base.py
rltorch/memory/multi_step.py
rltorch/memory/prioritized.py
rltorch/network/__init__.py
rltorch/network/base.py
rltorch/network/builder.py
rltorch/policy/__init__.py
rltorch/policy/categorical.py
rltorch/policy/gaussian.py
rltorch/q_function/__init__.py
rltorch/q_function/continuous.py
rltorch/q_function/discrete.py
rltorch-0.1.0.dist-info/LICENSE
rltorch-0.1.0.dist-info/METADATA
rltorch-0.1.0.dist-info/WHEEL
rltorch-0.1.0.dist-info/top_level.txt
rltorch-0.1.0.dist-info/RECORD
