Metadata-Version: 2.1
Name: rltorch
Version: 0.1.0
Summary: A simple framework for distributed reinforcement learning in PyTorch.
Home-page: https://github.com/ku2482/rltorch
Author: Toshiki Watanabe
Author-email: watanabe.toshiki@outlook.jp
License: MIT
Platform: UNKNOWN
Classifier: License :: OSI Approved :: MIT License
Classifier: Programming Language :: Python
Classifier: Programming Language :: Python :: 3
Classifier: Programming Language :: Python :: 3.6
Classifier: Programming Language :: Python :: Implementation :: CPython
Classifier: Programming Language :: Python :: Implementation :: PyPy
Requires-Python: >=3.6.0
Requires-Dist: numpy
Requires-Dist: torch
Requires-Dist: gym
